src/pyAparatAPI/__init__.py
src/pyAparatAPI/aparat.py
nanayuse-0.0.1.dist-info/METADATA
nanayuse-0.0.1.dist-info/WHEEL
nanayuse-0.0.1.dist-info/licenses/LICENSE
nanayuse-0.0.1.dist-info/RECORD
