Metadata-Version: 2.1
Name: nanayuse
Version: 0.0.1
Summary: A simple and easy to use Python implementation for the [Aparat API](https://www.aparat.com/api)
Project-URL: Homepage, https://github.com/AmirOfficiaI
Project-URL: Bug Tracker, https://github.com/AmirOfficiaI
Author-email: Ostad <CodingLovers.off@gmail.com>
License-File: LICENSE
Classifier: License :: OSI Approved :: MIT License
Classifier: Operating System :: OS Independent
Classifier: Programming Language :: Python :: 3
Requires-Python: >=3.7
